cat_python/__init__.py
cat_python/cat.py
cat_python/db.py
cat_python/py.typed
cat_python/types.py
catest-0.0.1a0.dist-info/METADATA
catest-0.0.1a0.dist-info/WHEEL
catest-0.0.1a0.dist-info/RECORD
