Metadata-Version: 2.3
Name: catest
Version: 0.0.1a0
Summary: Python client for running CAT tests in a Python codebase
Author: Mike Gehard
Author-email: mikegehard@artium.ai
Requires-Python: >=3.13,<4.0
Classifier: Programming Language :: Python :: 3
Classifier: Programming Language :: Python :: 3.13
